agenticlypay/__init__.py
agenticlypay/cli.py
agenticlypay/config.py
agenticlypay/connect.py
agenticlypay/models.py
agenticlypay/payments.py
agenticlypay/payouts.py
agenticlypay/stripe_client.py
agenticlypay/tax.py
agenticlypay/api/__init__.py
agenticlypay/api/main.py
agenticlypay/api/routes/__init__.py
agenticlypay/api/routes/connect.py
agenticlypay/api/routes/payments.py
agenticlypay/api/routes/payouts.py
agenticlypay/api/routes/tax.py
agenticlypay/api/routes/webhooks.py
agenticlypay/protocols/__init__.py
agenticlypay/protocols/acp.py
agenticlypay/protocols/ap2.py
agenticlypay/protocols/x402.py
agenticlypay-0.1.0.dist-info/licenses/LICENSE
agenticlypay-0.1.0.dist-info/METADATA
agenticlypay-0.1.0.dist-info/WHEEL
agenticlypay-0.1.0.dist-info/entry_points.txt
agenticlypay-0.1.0.dist-info/top_level.txt
agenticlypay-0.1.0.dist-info/RECORD
