Metadata-Version: 2.4
Name: agenticlypay
Version: 0.1.0
Summary: Python library and API for processing agentic payments (ACP, AP2, x402) via Stripe
Author-email: AgenticlyPay <support@agenticlypay.com>
License: MIT
Project-URL: Homepage, https://github.com/agenticlypay/agenticlypay
Project-URL: Documentation, https://agenticlypay-frontend-r6zgzqpgja-uc.a.run.app
Project-URL: Repository, https://github.com/agenticlypay/agenticlypay
Project-URL: Issues, https://github.com/agenticlypay/agenticlypay/issues
Keywords: stripe,payments,agentic,acp,ap2,x402,api,payment-processing,stripe-connect
Classifier: Development Status :: 3 - Alpha
Classifier: Intended Audience :: Developers
Classifier: License :: OSI Approved :: MIT License
Classifier: Programming Language :: Python :: 3
Classifier: Programming Language :: Python :: 3.11
Classifier: Programming Language :: Python :: 3.12
Classifier: Topic :: Software Development :: Libraries :: Python Modules
Classifier: Topic :: Office/Business :: Financial
Classifier: Topic :: Internet :: WWW/HTTP :: HTTP Servers
Requires-Python: >=3.11
License-File: LICENSE
Requires-Dist: stripe>=7.0.0
Requires-Dist: fastapi>=0.104.0
Requires-Dist: uvicorn[standard]>=0.24.0
Requires-Dist: python-dotenv>=1.0.0
Requires-Dist: pydantic>=2.5.0
Requires-Dist: pydantic-settings>=2.1.0
Requires-Dist: httpx>=0.25.0
Requires-Dist: python-multipart>=0.0.6
Provides-Extra: dev
Requires-Dist: pytest>=7.4.0; extra == "dev"
Requires-Dist: pytest-asyncio>=0.21.0; extra == "dev"
Requires-Dist: black>=23.11.0; extra == "dev"
Requires-Dist: ruff>=0.1.6; extra == "dev"
Dynamic: license-file
